Metadata-Version: 1.0
Name: AWS-pypi-exercise
Version: 0.1
Summary: Gaussian distributions
Home-page: UNKNOWN
Author: Kelvin Mwaka
Author-email: kevmwa@gmail.com
License: UNKNOWN
Platform: UNKNOWN
